dune_client/__init__.py
dune_client/client.py
dune_client/client_async.py
dune_client/interface.py
dune_client/models.py
dune_client/py.typed
dune_client/query.py
dune_client/types.py
dune_client/util.py
dune_client/api/__init__.py
dune_client/api/base.py
dune_client/api/custom.py
dune_client/api/execution.py
dune_client/api/extensions.py
dune_client/api/query.py
dune_client/api/table.py
dune_client/file/__init__.py
dune_client/file/base.py
dune_client/file/interface.py
dune_client-1.9.2.dist-info/METADATA
dune_client-1.9.2.dist-info/WHEEL
dune_client-1.9.2.dist-info/licenses/LICENSE
dune_client-1.9.2.dist-info/RECORD
