Metadata-Version: 2.4
Name: dune_client
Version: 1.9.2
Summary: A simple framework for interacting with Dune Analytics official API service.
Project-URL: Homepage, https://github.com/duneanalytics/dune-client
Project-URL: Repository, https://github.com/duneanalytics/dune-client
Project-URL: Issues, https://github.com/duneanalytics/dune-client/issues
Author-email: "Benjamin H. Smith & Dune Analytics" <ben@cow.fi>
License: Apache License Version 2.0
License-File: LICENSE
Classifier: License :: OSI Approved :: Apache Software License
Classifier: Operating System :: OS Independent
Classifier: Programming Language :: Python :: 3
Classifier: Programming Language :: Python :: 3.11
Classifier: Programming Language :: Python :: 3.12
Classifier: Programming Language :: Python :: 3.13
Requires-Python: >=3.11
Requires-Dist: aiohttp~=3.12.15
Requires-Dist: dataclasses-json~=0.6.4
Requires-Dist: deprecated~=1.2.18
Requires-Dist: ndjson~=0.3.1
Requires-Dist: python-dateutil~=2.9.0
Requires-Dist: requests~=2.32.5
